snakemake_storage_plugin_xrootd/__init__.py
snakemake_storage_plugin_xrootd-0.4.1.dist-info/METADATA
snakemake_storage_plugin_xrootd-0.4.1.dist-info/WHEEL
snakemake_storage_plugin_xrootd-0.4.1.dist-info/licenses/LICENSE
snakemake_storage_plugin_xrootd-0.4.1.dist-info/RECORD
